devops_environment/__init__.py
devops_environment/cli.py
devops_environment/devops_environment.py
devops_environment-0.0.6.data/scripts/devenv
devops_environment-0.0.6.dist-info/LICENSE
devops_environment-0.0.6.dist-info/METADATA
devops_environment-0.0.6.dist-info/WHEEL
devops_environment-0.0.6.dist-info/entry_points.txt
devops_environment-0.0.6.dist-info/top_level.txt
devops_environment-0.0.6.dist-info/RECORD
