Metadata-Version: 2.1
Name: devops-environment
Version: 0.0.6
Summary: Development environment for DevOps
Home-page: https://github.com/sjmiller609/devops_environment
Author: Steven Miller
Author-email: sjmiller609@gmail.com
License: MIT license
Keywords: devops_environment
Platform: UNKNOWN
Classifier: Development Status :: 2 - Pre-Alpha
Classifier: Intended Audience :: Developers
Classifier: License :: OSI Approved :: MIT License
Classifier: Natural Language :: English
Classifier: Programming Language :: Python :: 2
Classifier: Programming Language :: Python :: 2.7
Classifier: Programming Language :: Python :: 3
Classifier: Programming Language :: Python :: 3.4
Classifier: Programming Language :: Python :: 3.5
Classifier: Programming Language :: Python :: 3.6
Classifier: Programming Language :: Python :: 3.7
Requires-Dist: Click (>=6.0)
Requires-Dist: docker (==3.7.0)
